api2ch/__init__.py
api2ch/api.py
api2ch/config.py
api2ch/helpers.py
api2ch/utils.py
api2ch/models/__init__.py
api2ch/models/auxiliary.py
api2ch/models/base.py
api2ch/models/board.py
api2ch/models/file.py
api2ch/models/post.py
api2ch/models/request.py
api2ch/models/response.py
api2ch/models/thread.py
api2ch-1.2.1.dist-info/LICENSE
api2ch-1.2.1.dist-info/METADATA
api2ch-1.2.1.dist-info/WHEEL
api2ch-1.2.1.dist-info/top_level.txt
api2ch-1.2.1.dist-info/RECORD
