Metadata-Version: 2.1
Name: api2ch
Version: 1.2.1
Summary: Async API Wrapper for 2ch Imageboard with typings
Home-page: https://github.com/uburuntu/api2ch
Download-URL: https://github.com/uburuntu/api2ch/archive/master.zip
Author: uburuntu
Author-email: github@rmbk.me
License: MIT
Keywords: 2ch,dvach,api
Platform: all
Classifier: Development Status :: 5 - Production/Stable
Classifier: Framework :: AsyncIO
Classifier: Intended Audience :: Developers
Classifier: License :: OSI Approved :: MIT License
Classifier: Programming Language :: Python :: 3
Classifier: Typing :: Typed
License-File: LICENSE
Requires-Dist: aiofiles (>=0.5)
Requires-Dist: aiohttp (>=3.6)
Requires-Dist: pydantic (>=1.6)
Requires-Dist: requests (>=2.24)
Provides-Extra: dev
Requires-Dist: datamodel-code-generator (>=0.12) ; extra == 'dev'
Requires-Dist: codecov (>=2.0) ; extra == 'dev'
Requires-Dist: flake8 (>=4.0) ; extra == 'dev'
Requires-Dist: pytest (>=5.4) ; extra == 'dev'
Requires-Dist: pytest-asyncio (>=0.12) ; extra == 'dev'
Requires-Dist: pytest-cov (>=2.8) ; extra == 'dev'
Requires-Dist: transliterate (>=1.10) ; extra == 'dev'
